README.md
setup.py
TorchLanguage.egg-info/PKG-INFO
TorchLanguage.egg-info/SOURCES.txt
TorchLanguage.egg-info/dependency_links.txt
TorchLanguage.egg-info/not-zip-safe
TorchLanguage.egg-info/requires.txt
TorchLanguage.egg-info/top_level.txt
torchlanguage/__init__.py
torchlanguage/datasets/FileDirectory.py
torchlanguage/datasets/ReutersC50Dataset.py
torchlanguage/datasets/SFGramDataset.py
torchlanguage/datasets/__init__.py
torchlanguage/embeddings/CharacterEmbedding.py
torchlanguage/embeddings/__init__.py
torchlanguage/models/CGFS.py
torchlanguage/models/CNN3C.py
torchlanguage/models/CNNCTweet.py
torchlanguage/models/CNNEmbed.py
torchlanguage/models/CNNgram.py
torchlanguage/models/EGRU.py
torchlanguage/models/ELSTM.py
torchlanguage/models/__init__.py
torchlanguage/transforms/Character.py
torchlanguage/transforms/Character2Gram.py
torchlanguage/transforms/Character3Gram.py
torchlanguage/transforms/Compose.py
torchlanguage/transforms/DropOut.py
torchlanguage/transforms/Embedding.py
torchlanguage/transforms/FunctionWord.py
torchlanguage/transforms/GensimModel.py
torchlanguage/transforms/GloveVector.py
torchlanguage/transforms/HorizontalStack.py
torchlanguage/transforms/MaxIndex.py
torchlanguage/transforms/PartOfSpeech.py
torchlanguage/transforms/RandomSamples.py
torchlanguage/transforms/RemoveCharacter.py
torchlanguage/transforms/RemoveLines.py
torchlanguage/transforms/RemoveRegex.py
torchlanguage/transforms/Tag.py
torchlanguage/transforms/ToFrequencyVector.py
torchlanguage/transforms/ToIndex.py
torchlanguage/transforms/ToLength.py
torchlanguage/transforms/ToLower.py
torchlanguage/transforms/ToNGram.py
torchlanguage/transforms/ToOneHot.py
torchlanguage/transforms/ToUpper.py
torchlanguage/transforms/Token.py
torchlanguage/transforms/Transformer.py
torchlanguage/transforms/VerticalStack.py
torchlanguage/transforms/__init__.py
torchlanguage/utils/CrossValidation.py
torchlanguage/utils/__init__.py