Metadata-Version: 1.0
Name: TorchLanguage
Version: 0.1
Summary: A pyTorch toolkit for Natural Language Processing.
Home-page: UNKNOWN
Author: Nils Schaetti
Author-email: nils.schaetti@unine.ch
License: GPLv3
Platform: UNKNOWN
